[
  {
    "url": "https://api.github.com/repos/toml-lang/toml/releases/36268268",
    "assets_url": "https://api.github.com/repos/toml-lang/toml/releases/36268268/assets",
    "upload_url": "https://uploads.github.com/repos/toml-lang/toml/releases/36268268/assets{?name,label}",
    "html_url": "https://github.com/toml-lang/toml/releases/tag/1.0.0",
    "id": 36268268,
    "author": {
      "login": "pradyunsg",
      "id": 3275593,
      "node_id": "MDQ6VXNlcjMyNzU1OTM=",
      "avatar_url": "https://avatars.githubusercontent.com/u/3275593?v=4",
      "gravatar_id": "",
      "url": "https://api.github.com/users/pradyunsg",
      "html_url": "https://github.com/pradyunsg",
      "followers_url": "https://api.github.com/users/pradyunsg/followers",
      "following_url": "https://api.github.com/users/pradyunsg/following{/other_user}",
      "gists_url": "https://api.github.com/users/pradyunsg/gists{/gist_id}",
      "starred_url": "https://api.github.com/users/pradyunsg/starred{/owner}{/repo}",
      "subscriptions_url": "https://api.github.com/users/pradyunsg/subscriptions",
      "organizations_url": "https://api.github.com/users/pradyunsg/orgs",
      "repos_url": "https://api.github.com/users/pradyunsg/repos",
      "events_url": "https://api.github.com/users/pradyunsg/events{/privacy}",
      "received_events_url": "https://api.github.com/users/pradyunsg/received_events",
      "type": "User",
      "user_view_type": "public",
      "site_admin": false
    },
    "node_id": "MDc6UmVsZWFzZTM2MjY4MjY4",
    "tag_name": "1.0.0",
    "target_commitish": "master",
    "name": "Release 1.0.0",
    "draft": false,
    "prerelease": false,
    "created_at": "2021-01-11T20:34:40Z",
    "published_at": "2021-01-12T09:14:27Z",
    "assets": [],
    "tarball_url": "https://api.github.com/repos/toml-lang/toml/tarball/1.0.0",
    "zipball_url": "https://api.github.com/repos/toml-lang/toml/zipball/1.0.0",
    "body": "About time TOML hit 1.0.0!\r\n\r\n- Clarify how tables are created and defined.\r\n- Clarify and describe the top-level table.\r\n- Clarify that indentation before keys is ignored.\r\n- Clarify that indentation before table headers is ignored.\r\n- Clarify that indentation between array values is ignored.",
    "reactions": {
      "url": "https://api.github.com/repos/toml-lang/toml/releases/36268268/reactions",
      "total_count": 64,
      "+1": 17,
      "-1": 0,
      "laugh": 5,
      "hooray": 21,
      "confused": 0,
      "heart": 10,
      "rocket": 7,
      "eyes": 4
    }
  },
  {
    "url": "https://api.github.com/repos/toml-lang/toml/releases/32260755",
    "assets_url": "https://api.github.com/repos/toml-lang/toml/releases/32260755/assets",
    "upload_url": "https://uploads.github.com/repos/toml-lang/toml/releases/32260755/assets{?name,label}",
    "html_url": "https://github.com/toml-lang/toml/releases/tag/1.0.0-rc.3",
    "id": 32260755,
    "author": {
      "login": "pradyunsg",
      "id": 3275593,
      "node_id": "MDQ6VXNlcjMyNzU1OTM=",
      "avatar_url": "https://avatars.githubusercontent.com/u/3275593?v=4",
      "gravatar_id": "",
      "url": "https://api.github.com/users/pradyunsg",
      "html_url": "https://github.com/pradyunsg",
      "followers_url": "https://api.github.com/users/pradyunsg/followers",
      "following_url": "https://api.github.com/users/pradyunsg/following{/other_user}",
      "gists_url": "https://api.github.com/users/pradyunsg/gists{/gist_id}",
      "starred_url": "https://api.github.com/users/pradyunsg/starred{/owner}{/repo}",
      "subscriptions_url": "https://api.github.com/users/pradyunsg/subscriptions",
      "organizations_url": "https://api.github.com/users/pradyunsg/orgs",
      "repos_url": "https://api.github.com/users/pradyunsg/repos",
      "events_url": "https://api.github.com/users/pradyunsg/events{/privacy}",
      "received_events_url": "https://api.github.com/users/pradyunsg/received_events",
      "type": "User",
      "user_view_type": "public",
      "site_admin": false
    },
    "node_id": "MDc6UmVsZWFzZTMyMjYwNzU1",
    "tag_name": "1.0.0-rc.3",
    "target_commitish": "master",
    "name": "1.0.0-rc.3",
    "draft": false,
    "prerelease": true,
    "created_at": "2020-10-07T10:33:22Z",
    "published_at": "2020-10-07T10:36:36Z",
    "assets": [],
    "tarball_url": "https://api.github.com/repos/toml-lang/toml/tarball/1.0.0-rc.3",
    "zipball_url": "https://api.github.com/repos/toml-lang/toml/zipball/1.0.0-rc.3",
    "body": "* Clarify that comments and newlines are allowed before commas in arrays.\r\n* Mark the ABNF as canonical, and reference it from the text specification.\r\n"
  },
  {
    "url": "https://api.github.com/repos/toml-lang/toml/releases/29482769",
    "assets_url": "https://api.github.com/repos/toml-lang/toml/releases/29482769/assets",
    "upload_url": "https://uploads.github.com/repos/toml-lang/toml/releases/29482769/assets{?name,label}",
    "html_url": "https://github.com/toml-lang/toml/releases/tag/1.0.0-rc.2",
    "id": 29482769,
    "author": {
      "login": "pradyunsg",
      "id": 3275593,
      "node_id": "MDQ6VXNlcjMyNzU1OTM=",
      "avatar_url": "https://avatars.githubusercontent.com/u/3275593?v=4",
      "gravatar_id": "",
      "url": "https://api.github.com/users/pradyunsg",
      "html_url": "https://github.com/pradyunsg",
      "followers_url": "https://api.github.com/users/pradyunsg/followers",
      "following_url": "https://api.github.com/users/pradyunsg/following{/other_user}",
      "gists_url": "https://api.github.com/users/pradyunsg/gists{/gist_id}",
      "starred_url": "https://api.github.com/users/pradyunsg/starred{/owner}{/repo}",
      "subscriptions_url": "https://api.github.com/users/pradyunsg/subscriptions",
      "organizations_url": "https://api.github.com/users/pradyunsg/orgs",
      "repos_url": "https://api.github.com/users/pradyunsg/repos",
      "events_url": "https://api.github.com/users/pradyunsg/events{/privacy}",
      "received_events_url": "https://api.github.com/users/pradyunsg/received_events",
      "type": "User",
      "user_view_type": "public",
      "site_admin": false
    },
    "node_id": "MDc6UmVsZWFzZTI5NDgyNzY5",
    "tag_name": "1.0.0-rc.2",
    "target_commitish": "master",
    "name": "1.0.0-rc.2",
    "draft": false,
    "prerelease": true,
    "created_at": "2020-08-09T04:50:42Z",
    "published_at": "2020-08-09T04:57:15Z",
    "assets": [],
    "tarball_url": "https://api.github.com/repos/toml-lang/toml/tarball/1.0.0-rc.2",
    "zipball_url": "https://api.github.com/repos/toml-lang/toml/zipball/1.0.0-rc.2",
    "body": "\r\n* Create https://toml.io as the new primary location to read the TOML spec.\r\n* Clarify meaning of \"quotation marks\".\r\n* Clarify meaning of \"expected\" value ranges.\r\n* Clarify that EOF is allowed after key/value pair.\r\n* Clarify that the various styles for writing keys are equivalent.\r\n* Clarify that line-ending backslashes must be unescaped in multi-line strings.\r\n* Add examples for invalid float values.\r\n"
  },
  {
    "url": "https://api.github.com/repos/toml-lang/toml/releases/25167784",
    "assets_url": "https://api.github.com/repos/toml-lang/toml/releases/25167784/assets",
    "upload_url": "https://uploads.github.com/repos/toml-lang/toml/releases/25167784/assets{?name,label}",
    "html_url": "https://github.com/toml-lang/toml/releases/tag/v1.0.0-rc.1",
    "id": 25167784,
    "author": {
      "login": "pradyunsg",
      "id": 3275593,
      "node_id": "MDQ6VXNlcjMyNzU1OTM=",
      "avatar_url": "https://avatars.githubusercontent.com/u/3275593?v=4",
      "gravatar_id": "",
      "url": "https://api.github.com/users/pradyunsg",
      "html_url": "https://github.com/pradyunsg",
      "followers_url": "https://api.github.com/users/pradyunsg/followers",
      "following_url": "https://api.github.com/users/pradyunsg/following{/other_user}",
      "gists_url": "https://api.github.com/users/pradyunsg/gists{/gist_id}",
      "starred_url": "https://api.github.com/users/pradyunsg/starred{/owner}{/repo}",
      "subscriptions_url": "https://api.github.com/users/pradyunsg/subscriptions",
      "organizations_url": "https://api.github.com/users/pradyunsg/orgs",
      "repos_url": "https://api.github.com/users/pradyunsg/repos",
      "events_url": "https://api.github.com/users/pradyunsg/events{/privacy}",
      "received_events_url": "https://api.github.com/users/pradyunsg/received_events",
      "type": "User",
      "user_view_type": "public",
      "site_admin": false
    },
    "node_id": "MDc6UmVsZWFzZTI1MTY3Nzg0",
    "tag_name": "v1.0.0-rc.1",
    "target_commitish": "master",
    "name": "v1.0.0-rc.1",
    "draft": false,
    "prerelease": true,
    "created_at": "2020-04-03T11:12:20Z",
    "published_at": "2020-04-03T11:14:58Z",
    "assets": [],
    "tarball_url": "https://api.github.com/repos/toml-lang/toml/tarball/v1.0.0-rc.1",
    "zipball_url": "https://api.github.com/repos/toml-lang/toml/zipball/v1.0.0-rc.1",
    "body": "\r\n* Clarify in ABNF how quotes in multi-line basic and multi-line literal strings\r\n  are allowed to be used.\r\n* Leading zeroes in exponent parts of floats are permitted.\r\n* Clarify that control characters are not permitted in comments.\r\n* Clarify behavior of tables defined implicitly by dotted keys.\r\n* Clarify that inline tables are immutable.\r\n* Clarify that trailing commas are not allowed in inline tables.\r\n* Clarify in ABNF that UTF-16 surrogate code points (U+D800 - U+DFFF) are not\r\n  allowed in strings or comments.\r\n* Allow raw tab characters in basic strings and multi-line basic strings.\r\n* Allow heterogenous values in arrays.\r\n"
  },
  {
    "url": "https://api.github.com/repos/toml-lang/toml/releases/11865985",
    "assets_url": "https://api.github.com/repos/toml-lang/toml/releases/11865985/assets",
    "upload_url": "https://uploads.github.com/repos/toml-lang/toml/releases/11865985/assets{?name,label}",
    "html_url": "https://github.com/toml-lang/toml/releases/tag/v0.5.0",
    "id": 11865985,
    "author": {
      "login": "mojombo",
      "id": 1,
      "node_id": "MDQ6VXNlcjE=",
      "avatar_url": "https://avatars.githubusercontent.com/u/1?v=4",
      "gravatar_id": "",
      "url": "https://api.github.com/users/mojombo",
      "html_url": "https://github.com/mojombo",
      "followers_url": "https://api.github.com/users/mojombo/followers",
      "following_url": "https://api.github.com/users/mojombo/following{/other_user}",
      "gists_url": "https://api.github.com/users/mojombo/gists{/gist_id}",
      "starred_url": "https://api.github.com/users/mojombo/starred{/owner}{/repo}",
      "subscriptions_url": "https://api.github.com/users/mojombo/subscriptions",
      "organizations_url": "https://api.github.com/users/mojombo/orgs",
      "repos_url": "https://api.github.com/users/mojombo/repos",
      "events_url": "https://api.github.com/users/mojombo/events{/privacy}",
      "received_events_url": "https://api.github.com/users/mojombo/received_events",
      "type": "User",
      "user_view_type": "public",
      "site_admin": false
    },
    "node_id": "MDc6UmVsZWFzZTExODY1OTg1",
    "tag_name": "v0.5.0",
    "target_commitish": "master",
    "name": "v0.5.0",
    "draft": false,
    "prerelease": true,
    "created_at": "2018-07-10T21:44:12Z",
    "published_at": "2018-07-10T21:58:13Z",
    "assets": [],
    "tarball_url": "https://api.github.com/repos/toml-lang/toml/tarball/v0.5.0",
    "zipball_url": "https://api.github.com/repos/toml-lang/toml/zipball/v0.5.0",
    "body": "* Add dotted keys.\r\n* Add hex, octal, and binary integer formats.\r\n* Add special float values (inf, nan)\r\n* Rename Datetime to Offset Date-Time.\r\n* Add Local Date-Time.\r\n* Add Local Date.\r\n* Add Local Time.\r\n* Add ABNF specification.\r\n* Allow space (instead of T) to separate date and time in Date-Time.\r\n* Allow accidental whitespace between backslash and newline in the line\r\n  continuation operator in multi-line basic strings.\r\n* Specify that the standard file extension is `.toml`.\r\n* Specify that MIME type is `application/toml`\r\n* Clarify that U+007F is an escape character.\r\n* Clarify that keys are always strings.\r\n* Clarify that you cannot use array-of-table to append to a static array.\r\n* Clarify that a TOML file must be a valid UTF-8 document.\r\n* Clarify valid Array values.\r\n* Clarify that literal strings can be table keys.\r\n* Clarify that at least millisecond precision expected for Date-Time and Time.\r\n* Clarify that comments are OK in multiline arrays.\r\n* Clarify that +0, -0, +0.0, and -0.0 are valid and what they mean.\r\n* TOML has a logo!",
    "reactions": {
      "url": "https://api.github.com/repos/toml-lang/toml/releases/11865985/reactions",
      "total_count": 2,
      "+1": 2,
      "-1": 0,
      "laugh": 0,
      "hooray": 0,
      "confused": 0,
      "heart": 0,
      "rocket": 0,
      "eyes": 0
    }
  },
  {
    "url": "https://api.github.com/repos/toml-lang/toml/releases/947048",
    "assets_url": "https://api.github.com/repos/toml-lang/toml/releases/947048/assets",
    "upload_url": "https://uploads.github.com/repos/toml-lang/toml/releases/947048/assets{?name,label}",
    "html_url": "https://github.com/toml-lang/toml/releases/tag/v0.4.0",
    "id": 947048,
    "author": {
      "login": "mojombo",
      "id": 1,
      "node_id": "MDQ6VXNlcjE=",
      "avatar_url": "https://avatars.githubusercontent.com/u/1?v=4",
      "gravatar_id": "",
      "url": "https://api.github.com/users/mojombo",
      "html_url": "https://github.com/mojombo",
      "followers_url": "https://api.github.com/users/mojombo/followers",
      "following_url": "https://api.github.com/users/mojombo/following{/other_user}",
      "gists_url": "https://api.github.com/users/mojombo/gists{/gist_id}",
      "starred_url": "https://api.github.com/users/mojombo/starred{/owner}{/repo}",
      "subscriptions_url": "https://api.github.com/users/mojombo/subscriptions",
      "organizations_url": "https://api.github.com/users/mojombo/orgs",
      "repos_url": "https://api.github.com/users/mojombo/repos",
      "events_url": "https://api.github.com/users/mojombo/events{/privacy}",
      "received_events_url": "https://api.github.com/users/mojombo/received_events",
      "type": "User",
      "user_view_type": "public",
      "site_admin": false
    },
    "node_id": "MDc6UmVsZWFzZTk0NzA0OA==",
    "tag_name": "v0.4.0",
    "target_commitish": "main",
    "name": "v0.4.0",
    "draft": false,
    "prerelease": true,
    "created_at": "2015-02-12T20:30:29Z",
    "published_at": "2015-02-12T20:31:52Z",
    "assets": [],
    "tarball_url": "https://api.github.com/repos/toml-lang/toml/tarball/v0.4.0",
    "zipball_url": "https://api.github.com/repos/toml-lang/toml/zipball/v0.4.0",
    "body": "- Add Inline Table syntax.\n- Allow underscores in numbers.\n- Remove forward slash as an escapable character.\n- Unicode escapes must be scalar values.\n- Newline is now defined as LF or CRLF.\n"
  },
  {
    "url": "https://api.github.com/repos/toml-lang/toml/releases/692150",
    "assets_url": "https://api.github.com/repos/toml-lang/toml/releases/692150/assets",
    "upload_url": "https://uploads.github.com/repos/toml-lang/toml/releases/692150/assets{?name,label}",
    "html_url": "https://github.com/toml-lang/toml/releases/tag/v0.3.0",
    "id": 692150,
    "author": {
      "login": "mojombo",
      "id": 1,
      "node_id": "MDQ6VXNlcjE=",
      "avatar_url": "https://avatars.githubusercontent.com/u/1?v=4",
      "gravatar_id": "",
      "url": "https://api.github.com/users/mojombo",
      "html_url": "https://github.com/mojombo",
      "followers_url": "https://api.github.com/users/mojombo/followers",
      "following_url": "https://api.github.com/users/mojombo/following{/other_user}",
      "gists_url": "https://api.github.com/users/mojombo/gists{/gist_id}",
      "starred_url": "https://api.github.com/users/mojombo/starred{/owner}{/repo}",
      "subscriptions_url": "https://api.github.com/users/mojombo/subscriptions",
      "organizations_url": "https://api.github.com/users/mojombo/orgs",
      "repos_url": "https://api.github.com/users/mojombo/repos",
      "events_url": "https://api.github.com/users/mojombo/events{/privacy}",
      "received_events_url": "https://api.github.com/users/mojombo/received_events",
      "type": "User",
      "user_view_type": "public",
      "site_admin": false
    },
    "node_id": "MDc6UmVsZWFzZTY5MjE1MA==",
    "tag_name": "v0.3.0",
    "target_commitish": "main",
    "name": "v0.3.0",
    "draft": false,
    "prerelease": true,
    "created_at": "2014-11-10T15:42:56Z",
    "published_at": "2014-11-10T15:44:38Z",
    "assets": [],
    "tarball_url": "https://api.github.com/repos/toml-lang/toml/tarball/v0.3.0",
    "zipball_url": "https://api.github.com/repos/toml-lang/toml/zipball/v0.3.0",
    "body": "- Add scientific notation for floats.\n- Allow optional + prefix on integers.\n- Switch to RFC 3339 for datetimes (allowing offsets and fractional seconds).\n- Add multiline and literal strings.\n- Clarify what characters valid keys can contain.\n",
    "reactions": {
      "url": "https://api.github.com/repos/toml-lang/toml/releases/692150/reactions",
      "total_count": 1,
      "+1": 0,
      "-1": 0,
      "laugh": 1,
      "hooray": 0,
      "confused": 0,
      "heart": 0,
      "rocket": 0,
      "eyes": 0
    }
  },
  {
    "url": "https://api.github.com/repos/toml-lang/toml/releases/51191",
    "assets_url": "https://api.github.com/repos/toml-lang/toml/releases/51191/assets",
    "upload_url": "https://uploads.github.com/repos/toml-lang/toml/releases/51191/assets{?name,label}",
    "html_url": "https://github.com/toml-lang/toml/releases/tag/v0.2.0",
    "id": 51191,
    "author": {
      "login": "mojombo",
      "id": 1,
      "node_id": "MDQ6VXNlcjE=",
      "avatar_url": "https://avatars.githubusercontent.com/u/1?v=4",
      "gravatar_id": "",
      "url": "https://api.github.com/users/mojombo",
      "html_url": "https://github.com/mojombo",
      "followers_url": "https://api.github.com/users/mojombo/followers",
      "following_url": "https://api.github.com/users/mojombo/following{/other_user}",
      "gists_url": "https://api.github.com/users/mojombo/gists{/gist_id}",
      "starred_url": "https://api.github.com/users/mojombo/starred{/owner}{/repo}",
      "subscriptions_url": "https://api.github.com/users/mojombo/subscriptions",
      "organizations_url": "https://api.github.com/users/mojombo/orgs",
      "repos_url": "https://api.github.com/users/mojombo/repos",
      "events_url": "https://api.github.com/users/mojombo/events{/privacy}",
      "received_events_url": "https://api.github.com/users/mojombo/received_events",
      "type": "User",
      "user_view_type": "public",
      "site_admin": false
    },
    "node_id": "MDc6UmVsZWFzZTUxMTkx",
    "tag_name": "v0.2.0",
    "target_commitish": "main",
    "name": "v0.2.0",
    "draft": false,
    "prerelease": true,
    "created_at": "2013-09-24T16:24:27Z",
    "published_at": "2013-09-24T16:29:02Z",
    "assets": [],
    "tarball_url": "https://api.github.com/repos/toml-lang/toml/tarball/v0.2.0",
    "zipball_url": "https://api.github.com/repos/toml-lang/toml/zipball/v0.2.0",
    "body": "- Use \"table\" instead of \"key group\" terminology.\n- Add the ability to define nestable arrays of tables.\n",
    "reactions": {
      "url": "https://api.github.com/repos/toml-lang/toml/releases/51191/reactions",
      "total_count": 1,
      "+1": 0,
      "-1": 0,
      "laugh": 1,
      "hooray": 0,
      "confused": 0,
      "heart": 0,
      "rocket": 0,
      "eyes": 0
    }
  },
  {
    "url": "https://api.github.com/repos/toml-lang/toml/releases/183",
    "assets_url": "https://api.github.com/repos/toml-lang/toml/releases/183/assets",
    "upload_url": "https://uploads.github.com/repos/toml-lang/toml/releases/183/assets{?name,label}",
    "html_url": "https://github.com/toml-lang/toml/releases/tag/v0.1.0",
    "id": 183,
    "author": {
      "login": "mojombo",
      "id": 1,
      "node_id": "MDQ6VXNlcjE=",
      "avatar_url": "https://avatars.githubusercontent.com/u/1?v=4",
      "gravatar_id": "",
      "url": "https://api.github.com/users/mojombo",
      "html_url": "https://github.com/mojombo",
      "followers_url": "https://api.github.com/users/mojombo/followers",
      "following_url": "https://api.github.com/users/mojombo/following{/other_user}",
      "gists_url": "https://api.github.com/users/mojombo/gists{/gist_id}",
      "starred_url": "https://api.github.com/users/mojombo/starred{/owner}{/repo}",
      "subscriptions_url": "https://api.github.com/users/mojombo/subscriptions",
      "organizations_url": "https://api.github.com/users/mojombo/orgs",
      "repos_url": "https://api.github.com/users/mojombo/repos",
      "events_url": "https://api.github.com/users/mojombo/events{/privacy}",
      "received_events_url": "https://api.github.com/users/mojombo/received_events",
      "type": "User",
      "user_view_type": "public",
      "site_admin": false
    },
    "node_id": "MDc6UmVsZWFzZTE4Mw==",
    "tag_name": "v0.1.0",
    "target_commitish": "main",
    "name": "v0.1.0",
    "draft": false,
    "prerelease": true,
    "created_at": "2013-03-17T23:20:25Z",
    "published_at": "2013-03-17T23:22:25Z",
    "assets": [],
    "tarball_url": "https://api.github.com/repos/toml-lang/toml/tarball/v0.1.0",
    "zipball_url": "https://api.github.com/repos/toml-lang/toml/zipball/v0.1.0",
    "body": "- From Twitter rage to reality; TOML is now a thing.\n- First proper release.\n- TOML adheres to the SemVer standard for version numbers.\n",
    "reactions": {
      "url": "https://api.github.com/repos/toml-lang/toml/releases/183/reactions",
      "total_count": 3,
      "+1": 3,
      "-1": 0,
      "laugh": 0,
      "hooray": 0,
      "confused": 0,
      "heart": 0,
      "rocket": 0,
      "eyes": 0
    }
  }
]